Metadata-Version: 2.1
Name: dandanleinad-image-processing
Version: 0.0.1
Summary: image Processing Package using skimage
Home-page: https://github.com/DandanLeinad/image-processing-package
Author: Daniel
Requires-Python: >=3.8
Requires-Dist: numpy
Requires-Dist: setuptools
Requires-Dist: scikit-image
